shashankshahcalculator/__init__.py
shashankshahcalculator-0.1.dist-info/LICENSE.txt
shashankshahcalculator-0.1.dist-info/METADATA
shashankshahcalculator-0.1.dist-info/WHEEL
shashankshahcalculator-0.1.dist-info/top_level.txt
shashankshahcalculator-0.1.dist-info/RECORD
