Metadata-Version: 2.1
Name: shashankshahcalculator
Version: 0.1
Summary: This is very basic calculator made by shashank shah.
Author: Shashank Shah
Author-email: shashank.shah@crestdatasys.com
Classifier: Programming Language :: Python :: 3
Classifier: License :: OSI Approved :: MIT License
Classifier: Operating System :: OS Independent
License-File: LICENSE.txt
